README.txt
buildout.cfg
setup.py
src/zc/__init__.py
src/zc.security.egg-info/PKG-INFO
src/zc.security.egg-info/SOURCES.txt
src/zc.security.egg-info/dependency_links.txt
src/zc.security.egg-info/namespace_packages.txt
src/zc.security.egg-info/requires.txt
src/zc.security.egg-info/top_level.txt
src/zc/security/__init__.py
src/zc/security/configure.zcml
src/zc/security/i18n.py
src/zc/security/interfaces.py
src/zc/security/search.py
src/zc/security/search.txt
src/zc/security/tests.py
src/zc/security/browser/__init__.py
src/zc/security/browser/configure.zcml
src/zc/security/browser/queryview.pt
src/zc/security/browser/queryview.py
src/zc/security/browser/queryview.txt
src/zc/security/browser/tests.py
