Metadata-Version: 1.0
Name: zc.security
Version: 4.2.0
Summary: Principal-searching UI for Zope 3 Pluggable Authentication
Home-page: http://svn.zope.org/zc.sharing
Author: Zope Corporation
Author-email: zope3-dev@zope.org
License: ZPL 2.1
Keywords: zope3 security
Platform: UNKNOWN
Classifier: License :: OSI Approved :: Zope Public License
